fauna_auth/__init__.py
fauna_auth/oauth.py
fauna_auth/public_key.py
fauna_auth/scopes.py
fauna_auth/testing.py
fauna_auth/types.py
fauna_auth-0.0.10.dist-info/METADATA
fauna_auth-0.0.10.dist-info/WHEEL
fauna_auth-0.0.10.dist-info/RECORD
