Metadata-Version: 2.1
Name: fauna-auth
Version: 0.0.10
Summary: Helper library
Author: Edward FitzGerald
Author-email: edward.fitzgerald@fetch.ai
Requires-Python: >=3.9,<4.0
Classifier: Programming Language :: Python :: 3
Classifier: Programming Language :: Python :: 3.9
Classifier: Programming Language :: Python :: 3.10
Classifier: Programming Language :: Python :: 3.11
Classifier: Programming Language :: Python :: 3.12
Requires-Dist: fastapi (>=0.111.0,<0.112.0)
Requires-Dist: jwcrypto (>=1.5.0,<2.0.0)
